knativekafka/__init__.py
knativekafka/knativekafkaconsumer.py
knativekafka/knativekafkaproducer.py
knativekafka-0.4.0.dist-info/METADATA
knativekafka-0.4.0.dist-info/WHEEL
knativekafka-0.4.0.dist-info/top_level.txt
knativekafka-0.4.0.dist-info/RECORD
